Workbook

Sheet Developer Projects
A1: S.No | B1: Developer | C1: Project Name | D1: Location (Sector / Area) | E1: Project Type | F1: Status | G1: RERA No. | H1: Area (Acres) | I1: Towers | J1: Units | K1: Configuration | L1: Unit Size Range | M1: Price Range (approx.) | N1: Possession / Completion | O1: Key Amenities / Features | P1: Notes
A2: 1 | B2: Nirala India | C2: Nirala Greenshire Phase I | D2: Sector 18, Greater Noida | E2: Residential | F2: Completed
A3: 2 | B3: Nirala India | C3: Nirala Aspire Phase I | D3: Sector 16, Greater Noida West | E3: Residential | F3: Completed | J3: 176 | O3: Completed phase; new phases since launched
A4: 3 | B4: Nirala India | C4: Nirala Aspire Phase II | D4: Sector 16, Greater Noida West | E4: Residential | F4: Ongoing | J4: 950
A5: 4 | B5: Nirala India | C5: Nirala Grand | D5: Sector 1, Greater Noida West | E5: Residential | F5: Ongoing | H5: 10.5 | K5: 2/3/4 BHK | O5: Vastu-compliant; Central Brahmasthal with Banyan Tree; Grand Clubhouse, gym, indoor games; 35+ amenities | P5: Launched ~Dec 2025
A6: 5 | B6: Nirala India | C6: Nirala Estate (Phases 2-5) | D6: Techzone-IV, Greater Noida West | E6: Residential | F6: Ongoing | H6: 25 | I6: 21 | J6: 3600 | K6: 2/3 BHK | M6: From ~₹13,000/sq ft (2BHK ~₹1.29-1.31 Cr, 3BHK ~₹2.49 Cr) | N6: Ph.1 delivered 2017; Ph.2 May 2025; Ph.3&4 Dec 2026; Ph.5 Nov 2027 | O6: 45,000 sq ft clubhouse; 18% open green space; lift ratio ~1:48-1:72
A7: 6 | B7: Nirala India | C7: Nirala Gateway | D7: Sector 12, Greater Noida West | E7: Residential | F7: Ongoing
A8: 7 | B8: Nirala India | C8: Nirala Greenshire Phase II | D8: Sector 2, Noida Extension | E8: Residential | F8: Upcoming | K8: 2/3/4 BHK | O8: Connected to Greater Noida West Link Road
A9: 8 | B9: Nirala World | C9: Nirala Trio | D9: Sector 2, Greater Noida West | E9: Residential | F9: Ongoing | K9: 3 BHK (ultra-luxury) | N9: ~Oct 2026 (approx.) | O9: Central Green/park; 2.5 km from GNW Link Road | P9: Developed under Nirala World brand
A10: 9 | B10: Nirala World | C10: Nirala World (flagship residential) | D10: Greater Noida West | E10: Residential | F10: Ongoing | K10: 2/3/4 BHK
A11: 10 | B11: Nirala World | C11: Nirala World Commercial, Sector 12 | D11: Sector 12, Noida Extension | E11: Commercial | F11: Upcoming | K11: Retail, office space | O11: On Noida-Greater Noida Expressway
A12: 11 | B12: Unibera | C12: Unibera Towers | D12: Sector 1, Greater Noida | E12: Residential (+ commercial block) | F12: Completed | G12: UPRERAPRJ2537 | H12: 4.44 | I12: 5-7 | J12: 711 | K12: 2/3/4 BHK + Other | L12: 635-1475 sq ft | M12: ₹27.90L-48.00L (also cited up to ₹92.41L) | N12: Possession offered Nov 2019 (launched Aug 2016) | O12: Gym, power backup, badminton/basketball court, swimming pool, skating rink; 75% open space | P12: 21 floors; loans via ICICI Bank & PNB
A13: 12 | B13: Bhutani Group | C13: Bhutani Alphathum | D13: Sector 90, Noida | E13: Commercial | F13: Completed | I13: 3 | K13: IT offices, retail, food court | O13: LEED Gold rated; ~53,000 sq ft floor plates; inspired by Singapore architecture
A14: 13 | B14: Bhutani Group | C14: Bhutani Cyberthum | D14: Sector 140A, Noida | E14: Commercial | F14: Completed | K14: Office, retail, food court, co-working
A15: 14 | B15: Bhutani Group | C15: Bhutani Grandthum | D15: Noida Extension / Greater Noida West | E15: Commercial | F15: Completed | K15: Retail, office, co-working, food court | O15: Anchor brands: Allen Solly, Pantaloons, Miraj Cinemas, Reebok, Tata Westside, Van Heusen | P15: Co-branded with Group 108
A16: 15 | B16: Bhutani Group | C16: Bhutani Avenue 62 | D16: Sector 62, Noida | E16: Commercial | F16: Completed | K16: Retail | O16: 5 Lacs+ footfall potential; only retail destination in Sector 62 | P16: Interior waterfall (25m)
A17: 16 | B17: Bhutani Group | C17: Bhutani Experience | D17: Sector 32, Noida | E17: Residential (studio) | F17: Completed | J17: 286 | K17: Studio (0 BHK) | L17: 726-1141 sq ft | O17: Fully furnished, pre-leased 5-star studios | P17: 20 floors
A18: 17 | B18: Bhutani Group | C18: Bhutani City Center 150 | D18: Sector 150, Noida | E18: Commercial | F18: Ongoing | K18: High-street retail, entertainment
A19: 18 | B19: Group 108 | C19: iThum | D19: Sector 62, Noida | E19: Commercial | F19: Completed | O19: Flagship commercial project cited alongside Parmesh Complex, Delhi
A20: 19 | B20: Group 108 | C20: Grandthum | D20: Greater Noida West | E20: Mixed (Residential + Commercial) | F20: Ongoing | K20: Residential + commercial | O20: Co-developed under Bhutani/Group 108 branding
A21: 20 | B21: Group 108 | C21: One FNG | D21: Sector 142, Noida | E21: Commercial | F21: Upcoming | G21: UPRERAPRJ279516 | H21: 14.46 | K21: Office, retail | M21: From ₹60,00,000 | N21: ~2028 | O21: Adjoins Advant Tower & Noida Metro Sector 142 station | P21: Leasehold
A22: 21 | B22: Gulsan Group | C22: Gulshan Dynasty | D22: Greater Noida West / Noida | E22: Residential | F22: Ongoing | N22: Possession available soon | O22: Flagship luxury development | P22: Nearing completion
A23: 22 | B23: Gulsan Group | C23: Gulshan Avante | D23: Greater Noida West | E23: Residential | F23: Ongoing | K23: 4-bedroom luxury concept
A24: 23 | B24: Gulsan Group | C24: Gulshan Bellina | D24: Sector 16, Greater Noida | E24: Residential | F24: Completed | K24: 2/3 BHK | N24: Ready to move | O24: Central lawn, open-air theatre, yoga/meditation decks, gym, pool | P24: 36-year legacy brand
A25: 24 | B25: Gulsan Group | C25: Gulshan Botnia | D25: Sector 144, Noida | E25: Residential | F25: Completed | K25: 2/3 BHK
A26: 25 | B26: Gulsan Group | C26: Gulshan Botnia Phase 2 | D26: Sector 144, Noida | E26: Residential | F26: Upcoming | K26: 2/3 BHK | O26: Clubhouse, jogging track, indoor games, rainwater harvesting, solar lighting
A27: 26 | B27: Gulsan Group | C27: Gulshan Vivante | D27: Sector 137, Noida | E27: Residential | F27: Completed | K27: 2/3 BHK | O27: Clubhouse, pool, landscaped gardens
A28: 27 | B28: Gulsan Group | C28: Gulshan Ikebana | D28: Sector 143, Noida | E28: Residential | F28: Completed
A29: 28 | B29: Gulsan Group | C29: Gulshan One29 | D29: Sector 129, Noida Expressway | E29: Commercial | F29: Completed | O29: One of Gulshan's prime commercial projects
A30: 29 | B30: ATS | C30: ATS One Hamlet | D30: Sector 50, Noida | E30: Residential | F30: Completed | H30: 14.5 | J30: 352 | K30: 3/4 BHK | L30: 1636-3115 sq ft | P30: IRR of 54% recorded on an early ASK Group exit
A31: 30 | B31: ATS | C31: ATS Greens II | D31: Sector 50, Noida | E31: Residential | F31: Completed | N31: Ready to move
A32: 31 | B32: ATS | C32: ATS Pristine Phase 2 | D32: Sector 150, Noida | E32: Residential | F32: Ongoing | J32: 113 | K32: Luxury apartments | O32: Connected to Noida-Greater Noida & Yamuna Expressways
A33: 32 | B33: ATS | C33: ATS Dolce Phase 2 | D33: Sector Zeta-1, Greater Noida West | E33: Residential | F33: Ongoing | O33: New phase recently launched
A34: 33 | B34: ATS | C34: ATS Destinaire | D34: Sector 1, Greater Noida West | E34: Residential | F34: Ongoing | H34: 4.78 (forest area) | K34: 3/4 BHK (HIG) | L34: 1900-2550 sq ft | O34: Miyawaki-technique forest area; low-density living
A35: 34 | B35: ATS | C35: ATS Homekraft Happy Trails | D35: Greater Noida | E35: Residential | F35: Completed | K35: 2/3 BHK | O35: Gated society
A36: 35 | B36: ATS | C36: ATS Dolce | D36: Sector Zeta-1, Greater Noida | E36: Residential | F36: Completed | H36: 14 | K36: 2/3/4 BHK | L36: 1240-2800 sq ft | O36: 7 km from Pari Chowk; near Knowledge Park & Taj Yamuna Expressway
A37: 36 | B37: ATS | C37: ATS Allure | D37: Yamuna Expressway, Greater Noida | E37: Residential | F37: Completed | K37: 2/3 BHK | N37: Completed March 2021 | O37: 88.62K sq m central park | P37: Low-density lifestyle homes
A38: 37 | B38: Experion Group | C38: Experion Elements | D38: Central Noida (Sector 45 area) | E38: Residential | F38: Ongoing | G38: UPRERAPRJ953234 (Ph.II) | O38: Grand Cineplex with large 4K LED screen & Dolby; EV charging per unit | P38: Building plan approved Jan 2024
A39: 38 | B39: Experion Group | C39: Experion Saatori / Sector 151 | D39: Sector 151, Noida | E39: Residential | F39: Upcoming | H39: 5 | K39: 3/4 BHK | N39: Soft launch; RERA registration underway | O39: Clubhouse, pool, gym, sports courts, smart home automation
A40: 39 | B40: Godrej Group | C40: Godrej Golf Links (Exquisite / Windsor / Park Avenue / The Suites / Evoke) | D40: Sector 27, Greater Noida | E40: Residential | F40: Completed | J40: Windsor 114; Park Avenue 1158; The Suites 176 | K40: 2-4 BHK, villas (Evoke) | O40: Township within Godrej Golf Links; 4-6 km from Noida-GN & Yamuna Expressways
A41: 40 | B41: Godrej Group | C41: Godrej Arden | D41: Sigma 3, Greater Noida | E41: Residential | F41: Ongoing | H41: 9.58 | I41: 9 | J41: 956 | K41: 2/3/4 BHK | L41: 730-1547 sq ft
A42: 41 | B42: Godrej Group | C42: Godrej Majesty | D42: Sector 12, Greater Noida West | E42: Residential | F42: Upcoming | H42: 8 | K42: 3/4 BHK | L42: 1754-2575 sq ft | M42: From ₹2.91 Cr | O42: Massive clubhouse; green living focus | P42: Newly launched
A43: 42 | B43: Godrej Group | C43: Godrej Woods | D43: Sector 43, Noida | E43: Residential | F43: Ongoing | G43: UPRERAPRJ13521 | N43: Final phases by Jan 2027 | P43: Forest-themed; partially ready
A44: 43 | B44: Godrej Group | C44: Godrej Tropical Isle | D44: Sector 146, Noida | E44: Residential | F44: Upcoming | G44: UPRERAPRJ303390 | H44: 6.17 | I44: 5 | K44: 3/4 BHK | L44: 1800-3250 sq ft | M44: From ₹3.26 Cr | N44: Launched late 2023; possession Feb 2030 | O44: Floating clubhouse, beach decks (island theme)
A45: 44 | B45: Godrej Group | C45: Godrej Palm Retreat 2 | D45: Sector 150, Noida | E45: Residential | F45: Ongoing | J45: 385
A46: 45 | B46: Godrej Group | C46: Godrej Nurture Phase 2 | D46: Sector 150, Noida | E46: Residential | F46: Ongoing | J46: 456 | K46: Affordable housing
A47: 46 | B47: GYGY Group | C47: GYGY Mentis | D47: Sector 140, Noida | E47: Commercial | F47: Ongoing | G47: UPRERAPRJ251909 | H47: 4.94-6 (sources vary) | I47: 3 | J47: 24+ | K47: IT offices, retail, food court, anchor shops | L47: 100-535 sq ft | M47: ₹29.00L-42.80L | N47: Expected March 2028 | O47: Swimming pool, gym, clubhouse, sky bar, cafe | P47: 24 floors per tower; up to 12% assured returns cited
A48: 47 | B48: GYGY Group | C48: GYGY FiveO | D48: Sector 50, Noida | E48: Commercial | F48: Ongoing | K48: Studio spaces, retail, cafes, restaurants, entertainment | O48: Near multiple metro stations
A49: 48 | B49: EON Group | C49: Fairfox EON (Eye of Noida) | D49: Sector 140A, Noida | E49: Commercial | F49: Ongoing | G49: UPRERAPRJ211016 (Block-A) | H49: 13.65 | I49: 4 | K49: Office spaces, retail shops, anchor spaces, food court, sky bar | M49: Office from ~₹55L; Retail from ~₹87L | O49: IGBC Gold rated; sustainable design | P49: 15 floors per tower; developer: Fairfox IT Infra
A50: 49 | B50: CRC Group | C50: The Peridona | D50: Jaypee Greens Golf Course, Greater Noida | E50: Residential | F50: Upcoming | K50: Ultra-luxury experiential residences | P50: Development outlay ~₹15 billion (excl. land); unveiled July 2025
A51: 50 | B51: Purvanchal Group | C51: Purvanchal Royal City Phase I | D51: Sector Chi-5, Greater Noida | E51: Residential | F51: Completed | G51: UPRERAPRJ3137 | H51: 13.8 | I51: 17 (combined w/ Ph.2) | K51: 3/4/5 BHK, duplexes | L51: 1735-2075 sq ft (3BHK) | M51: ₹1.80-3.34 Cr | N51: Launched Jun 2015; possession by Mar 2019 | O51: 100,000 sq ft clubhouse, 2 pools, gym, mini theatre, yoga zones | P51: Brick construction
A52: 51 | B52: Purvanchal Group | C52: Purvanchal Royal City Phase II | D52: Sector Chi-5, Greater Noida | E52: Residential | F52: Completed | G52: UPRERAPRJ295195 | H52: 8.8 | K52: 3 BHK & 3BHK+1 | N52: Started Feb 2019; delivered Dec 2023 | O52: Mivan technology construction; 3,703 parking spaces; ~70% open area | P52: 22 acres combined with Phase I
A53: 52 | B53: Purvanchal Group | C53: Purvanchal Silver City II | D53: Greater Noida | E53: Residential | F53: Completed
A54: 53 | B54: Purvanchal Group | C54: Purvanchal Heights | D54: Greater Noida | E54: Residential | F54: Completed
A55: 54 | B55: Purvanchal Group | C55: Purvanchal Royal City II | D55: Sector Chi-V, Yamuna Expressway, Greater Noida | E55: Residential | F55: Ongoing | G55: UPRERAPRJ295195 | J55: 1226 | M55: ₹1.14 Cr | P55: Construction status: Mid Stage
A56: 55 | B56: ABA Corp | C56: Orange County | D56: Noida | E56: Residential | F56: Completed | O56: Flagship delivered project
A57: 56 | B57: ABA Corp | C57: Cleo County | D57: Sector 121, Noida | E57: Residential | F57: Completed | K57: 3/4 BHK | O57: Clubhouse, swimming pool, landscaped gardens | P57: Rainwater harvesting, energy-efficient systems
A58: 57 | B58: ABA Corp | C58: Cherry County | D58: Greater Noida West | E58: Residential | F58: Ongoing | K58: 2/3/4 BHK | L58: 891-2232 sq ft | P58: 30-year legacy brand; also delivered Orange County & Cleo County
A59: 58 | B59: ACE Group | C59: ACE City / ACE Aspire / ACE Golfshire | D59: Greater Noida | E59: Residential | F59: Completed | O59: Delivered projects
A60: 59 | B60: ACE Group | C60: ACE Palm Floors | D60: Gurugram | E60: Residential | F60: Completed | G60: RC/REP/HARERA/GGM/439-449/2021 | H60: 50 | K60: Plots & floors | P60: 50-acre township
A61: 60 | B61: ACE Group | C61: ACE Divino | D61: Sector 1, Greater Noida West | E61: Residential | F61: Completed | G61: UPRERAPRJ6734 | H61: 10.41 | K61: 2/3/4 BHK, garden floors, penthouses | O61: 75%+ open green space; MIVAN technology; 3-sided open plot | P61: Financed by Tata Capital Housing Finance
A62: 61 | B62: ACE Group | C62: ACE Parkway | D62: Greater Noida | E62: Residential | F62: Completed | G62: UPRERAPRJ4514 | P62: Designed by Hafeez Contractor; interiors by Gauri Khan
A63: 62 | B63: ACE Group | C63: ACE Starlit | D63: Sector 152, Noida | E63: Residential | F63: Completed | G63: UPRERAPRJ677294 | H63: 6.79 | I63: 5 | J63: 492 | K63: 2/3 BHK | M63: 2BHK from ₹1.25 Cr | O63: 80% green area; corner plot | P63: 5 towers of 26 floors each; ready to move
A64: 63 | B64: ACE Group | C64: ACE Terra | D64: Noida / Greater Noida | E64: Residential | F64: Ongoing | G64: UPRERAPRJ683816
A65: 64 | B65: ACE Group | C65: ACE Han'ei | D65: Noida / Greater Noida | E65: Residential | F65: Ongoing | G65: UPRERAPRJ677887
A66: 65 | B66: ACE Group | C66: ACE Estate | D66: Noida / Greater Noida | E66: Residential | F66: Ongoing | G66: UPRERAPRJ442226
A67: 66 | B67: ACE Group | C67: ACE Acreville | D67: Yamuna Expressway, Greater Noida | E67: Residential | F67: Upcoming | G67: UPRERAPRJ248777 | P67: RERA registered March 2025
A68: 67 | B68: ACE Group | C68: ACE Verde | D68: Sector 22A, Yamuna Expressway, Greater Noida | E68: Residential | F68: Upcoming | G68: UPRERAPRJ913692 | H68: 8 | I68: 7 | J68: 1287 | K68: 3 BHK | L68: From 1818 sq ft | O68: Low-density, 7 towers | P68: RERA registered March 2025
A69: 68 | B69: ACE Group | C69: ACE-Mahagun Medalleo | D69: Noida / Greater Noida | E69: Residential | F69: Ongoing | G69: UPRERAPRJ125561
A70: 69 | B70: ACE Group | C70: ACE Hive | D70: Sector 22A, Yamuna Expressway | E70: Commercial | F70: Upcoming | G70: UPRERAPRJ939595 | P70: RERA registered March 2025
A71: 70 | B71: ACE Group | C71: ACE YXP | D71: Sector 22D, Yamuna Expressway | E71: Commercial | F71: Ongoing | G71: UPRERAPRJ397607 | O71: Near Jewar International Airport
A72: 71 | B72: ACE Group | C72: ACE 153 | D72: Sector 153, Noida | E72: Commercial | F72: Ongoing | G72: UPRERAPRJ423807
A73: 72 | B73: ACE Group | C73: ACE Capitol | D73: Sector 132, Noida Expressway | E73: Commercial | F73: Ongoing
A74: 73 | B74: ACE Group | C74: ACE Edit | D74: Noida / Greater Noida | E74: Commercial | F74: Ongoing | G74: UPRERAPRJ467686 | P74: RERA registered Sept 2025
A75: 74 | B75: ACE Group | C75: ACE Medley Avenue | D75: Noida / Greater Noida | E75: Commercial | F75: Completed | G75: UPRERAPRJ348653
A76: 75 | B76: Prestige Group | C76: Prestige Sector 150, Noida Expressway | D76: Sector 150, Noida | E76: Residential | F76: Upcoming | H76: 14.83 | K76: 2/3/4 BHK | L76: 1300-5200 sq ft | P76: First Prestige Group project in Noida
A77: 76 | B77: Prestige Group | C77: Prestige Sector 62, Noida | D77: Sector 62, Noida | E77: Residential | F77: Upcoming | P77: Announced new launch
A78: 77 | B78: Gaursons Group | C78: Gaur City (Sector 4) | D78: Sector 4, Greater Noida West | E78: Residential | F78: Completed | H78: 125 | K78: 2 BHK | L78: 1075-1165 sq ft | M78: ₹40.31L-43.68L | P78: Flagship township
A79: 78 | B79: Gaursons Group | C79: Gaur City 2 - 14th Avenue | D79: Greater Noida West | E79: Residential | F79: Ongoing | G79: UPRERAPRJ6742 | K79: 2/3 BHK | M79: From ₹95L
A80: 79 | B80: Gaursons Group | C80: Gaur City - 7th Avenue | D80: Greater Noida West | E80: Residential | F80: Ongoing | G80: UPRERAPRJ6695 | K80: 2/3 BHK | M80: From ₹90L
A81: 80 | B81: Gaursons Group | C81: Gaur Yamuna City (16th/32nd Park View, Villas) | D81: Yamuna Expressway | E81: Residential | F81: Ongoing | K81: Apartments, villas, independent floors | P81: Supreme Court monitored housing project
A82: 81 | B82: Gaursons Group | C82: Gaur Atulyam | D82: Techzone 4, Greater Noida | E82: Residential | F82: Ongoing
A83: 82 | B83: Gaursons Group | C83: Gaur City Center | D83: Greater Noida West | E83: Commercial | F83: Ongoing | G83: UPRERAPRJ4780 | K83: Residential + retail | M83: From ₹45L
A84: 83 | B84: Gaursons Group | C84: Gaur City Mall (Office Spaces / Gaur Suites) | D84: Gaur Chowk, Greater Noida West | E84: Commercial | F84: Ongoing | G84: UPRERAPRJ6934 | K84: Office space, serviced suites | M84: Office from ₹25L; Suites from ₹62L
A85: 84 | B85: Gaursons Group | C85: Gaur Chowk Mall | D85: Greater Noida West | E85: Commercial | F85: Ongoing | G85: UPRERAPRJ6934 | K85: Retail (leasing) | P85: Leasing option available
A86: 85 | B86: Gaursons Group | C86: Gaur Green City / Heights / Green Avenue / Green Vista / Homes / Ganga / Grandeur / Global Village / Cascades | D86: Noida / Ghaziabad / Greater Noida | E86: Residential | F86: Completed | P86: Delivered legacy portfolio (65+ projects delivered group-wide)

Sheet Summary
A1: Developer | B1: Total Projects Listed | C1: Completed | D1: Ongoing | E1: Upcoming
A2: Nirala India | B2: =COUNTIF('Developer Projects'!$B$2:$B$86,A2) -> 7 | C2: =COUNTIFS('Developer Projects'!$B$2:$B$86,A2,'Developer Projects'!$F$2:$F$86,"Completed") -> 2 | D2: =COUNTIFS('Developer Projects'!$B$2:$B$86,A2,'Developer Projects'!$F$2:$F$86,"Ongoing") -> 4 | E2: =COUNTIFS('Developer Projects'!$B$2:$B$86,A2,'Developer Projects'!$F$2:$F$86,"Upcoming") -> 1
A3: Nirala World | B3: =COUNTIF('Developer Projects'!$B$2:$B$86,A3) -> 3 | C3: =COUNTIFS('Developer Projects'!$B$2:$B$86,A3,'Developer Projects'!$F$2:$F$86,"Completed") -> 0 | D3: =COUNTIFS('Developer Projects'!$B$2:$B$86,A3,'Developer Projects'!$F$2:$F$86,"Ongoing") -> 2 | E3: =COUNTIFS('Developer Projects'!$B$2:$B$86,A3,'Developer Projects'!$F$2:$F$86,"Upcoming") -> 1
A4: Unibera | B4: =COUNTIF('Developer Projects'!$B$2:$B$86,A4) -> 1 | C4: =COUNTIFS('Developer Projects'!$B$2:$B$86,A4,'Developer Projects'!$F$2:$F$86,"Completed") -> 1 | D4: =COUNTIFS('Developer Projects'!$B$2:$B$86,A4,'Developer Projects'!$F$2:$F$86,"Ongoing") -> 0 | E4: =COUNTIFS('Developer Projects'!$B$2:$B$86,A4,'Developer Projects'!$F$2:$F$86,"Upcoming") -> 0
A5: Bhutani Group | B5: =COUNTIF('Developer Projects'!$B$2:$B$86,A5) -> 6 | C5: =COUNTIFS('Developer Projects'!$B$2:$B$86,A5,'Developer Projects'!$F$2:$F$86,"Completed") -> 5 | D5: =COUNTIFS('Developer Projects'!$B$2:$B$86,A5,'Developer Projects'!$F$2:$F$86,"Ongoing") -> 1 | E5: =COUNTIFS('Developer Projects'!$B$2:$B$86,A5,'Developer Projects'!$F$2:$F$86,"Upcoming") -> 0
A6: Group 108 | B6: =COUNTIF('Developer Projects'!$B$2:$B$86,A6) -> 3 | C6: =COUNTIFS('Developer Projects'!$B$2:$B$86,A6,'Developer Projects'!$F$2:$F$86,"Completed") -> 1 | D6: =COUNTIFS('Developer Projects'!$B$2:$B$86,A6,'Developer Projects'!$F$2:$F$86,"Ongoing") -> 1 | E6: =COUNTIFS('Developer Projects'!$B$2:$B$86,A6,'Developer Projects'!$F$2:$F$86,"Upcoming") -> 1
A7: Gulsan Group | B7: =COUNTIF('Developer Projects'!$B$2:$B$86,A7) -> 8 | C7: =COUNTIFS('Developer Projects'!$B$2:$B$86,A7,'Developer Projects'!$F$2:$F$86,"Completed") -> 5 | D7: =COUNTIFS('Developer Projects'!$B$2:$B$86,A7,'Developer Projects'!$F$2:$F$86,"Ongoing") -> 2 | E7: =COUNTIFS('Developer Projects'!$B$2:$B$86,A7,'Developer Projects'!$F$2:$F$86,"Upcoming") -> 1
A8: ATS | B8: =COUNTIF('Developer Projects'!$B$2:$B$86,A8) -> 8 | C8: =COUNTIFS('Developer Projects'!$B$2:$B$86,A8,'Developer Projects'!$F$2:$F$86,"Completed") -> 5 | D8: =COUNTIFS('Developer Projects'!$B$2:$B$86,A8,'Developer Projects'!$F$2:$F$86,"Ongoing") -> 3 | E8: =COUNTIFS('Developer Projects'!$B$2:$B$86,A8,'Developer Projects'!$F$2:$F$86,"Upcoming") -> 0
A9: Experion Group | B9: =COUNTIF('Developer Projects'!$B$2:$B$86,A9) -> 2 | C9: =COUNTIFS('Developer Projects'!$B$2:$B$86,A9,'Developer Projects'!$F$2:$F$86,"Completed") -> 0 | D9: =COUNTIFS('Developer Projects'!$B$2:$B$86,A9,'Developer Projects'!$F$2:$F$86,"Ongoing") -> 1 | E9: =COUNTIFS('Developer Projects'!$B$2:$B$86,A9,'Developer Projects'!$F$2:$F$86,"Upcoming") -> 1
A10: Godrej Group | B10: =COUNTIF('Developer Projects'!$B$2:$B$86,A10) -> 7 | C10: =COUNTIFS('Developer Projects'!$B$2:$B$86,A10,'Developer Projects'!$F$2:$F$86,"Completed") -> 1 | D10: =COUNTIFS('Developer Projects'!$B$2:$B$86,A10,'Developer Projects'!$F$2:$F$86,"Ongoing") -> 4 | E10: =COUNTIFS('Developer Projects'!$B$2:$B$86,A10,'Developer Projects'!$F$2:$F$86,"Upcoming") -> 2
A11: GYGY Group | B11: =COUNTIF('Developer Projects'!$B$2:$B$86,A11) -> 2 | C11: =COUNTIFS('Developer Projects'!$B$2:$B$86,A11,'Developer Projects'!$F$2:$F$86,"Completed") -> 0 | D11: =COUNTIFS('Developer Projects'!$B$2:$B$86,A11,'Developer Projects'!$F$2:$F$86,"Ongoing") -> 2 | E11: =COUNTIFS('Developer Projects'!$B$2:$B$86,A11,'Developer Projects'!$F$2:$F$86,"Upcoming") -> 0
A12: EON Group | B12: =COUNTIF('Developer Projects'!$B$2:$B$86,A12) -> 1 | C12: =COUNTIFS('Developer Projects'!$B$2:$B$86,A12,'Developer Projects'!$F$2:$F$86,"Completed") -> 0 | D12: =COUNTIFS('Developer Projects'!$B$2:$B$86,A12,'Developer Projects'!$F$2:$F$86,"Ongoing") -> 1 | E12: =COUNTIFS('Developer Projects'!$B$2:$B$86,A12,'Developer Projects'!$F$2:$F$86,"Upcoming") -> 0
A13: CRC Group | B13: =COUNTIF('Developer Projects'!$B$2:$B$86,A13) -> 1 | C13: =COUNTIFS('Developer Projects'!$B$2:$B$86,A13,'Developer Projects'!$F$2:$F$86,"Completed") -> 0 | D13: =COUNTIFS('Developer Projects'!$B$2:$B$86,A13,'Developer Projects'!$F$2:$F$86,"Ongoing") -> 0 | E13: =COUNTIFS('Developer Projects'!$B$2:$B$86,A13,'Developer Projects'!$F$2:$F$86,"Upcoming") -> 1
... A18: Gaursons Group | B18: =COUNTIF('Developer Projects'!$B$2:$B$86,A18) -> 9 | C18: =COUNTIFS('Developer Projects'!$B$2:$B$86,A18,'Developer Projects'!$F$2:$F$86,"Completed") -> 2 | D18: =COUNTIFS('Developer Projects'!$B$2:$B$86,A18,'Developer Projects'!$F$2:$F$86,"Ongoing") -> 7 | E18: =COUNTIFS('Developer Projects'!$B$2:$B$86,A18,'Developer Projects'!$F$2:$F$86,"Upcoming") -> 0

Sheet Notes
A1: Source & methodology
A2: - Compiled from public listings (developer websites, RERA-linked project pages, and portals such as 99acres, Square Yards, WhiteHat Realty, 360PropGuide, CommercialNoida) as of Aug 2026.
A3: - Blank cells mean that detail wasn't stated in the sources found — not that it's zero. Fill in from the developer's brochure/RERA filing where needed.
A4: - 'Status' reflects the most recently stated construction/possession status; large multi-phase projects show the status of their active/latest phase.
A5: - Some rows group several related sub-projects under one entry (e.g. Godrej Golf Links towers, delivered Gaursons legacy portfolio) — split into one row per RERA registration if your site needs that granularity.
A6: - Price ranges, unit counts and areas are as published at time of research and can shift — treat as indicative, not final.
A7: - Images were not included: bulk-downloading/redistributing developer marketing photos raises copyright issues, and this environment has no general internet file-download access. Request an official image pack from each developer's marketing team, or license renders/stock instead.
A8: - Verify RERA numbers, unit counts and possession dates directly on https://www.up-rera.in/projects before publishing on the website.
